negmas_geniusweb_bridge/__init__.py
negmas_geniusweb_bridge/anac2020/__init__.py
negmas_geniusweb_bridge/anac2020/agent_kt/__init__.py
negmas_geniusweb_bridge/anac2020/agent_kt/agent_kt.py
negmas_geniusweb_bridge/anac2020/agent_p1_damo/__init__.py
negmas_geniusweb_bridge/anac2020/agent_p1_damo/agent_p1_damo.py
negmas_geniusweb_bridge/anac2020/agent_xx/__init__.py
negmas_geniusweb_bridge/anac2020/agent_xx/agent_xx.py
negmas_geniusweb_bridge/anac2020/ahbune_agent/__init__.py
negmas_geniusweb_bridge/anac2020/ahbune_agent/ahbune_agent.py
negmas_geniusweb_bridge/anac2020/anaconda/__init__.py
negmas_geniusweb_bridge/anac2020/anaconda/anaconda.py
negmas_geniusweb_bridge/anac2020/angel/__init__.py
negmas_geniusweb_bridge/anac2020/angel/angel.py
negmas_geniusweb_bridge/anac2020/azar_agent/__init__.py
negmas_geniusweb_bridge/anac2020/azar_agent/azar_agent.py
negmas_geniusweb_bridge/anac2020/bling_bling/__init__.py
negmas_geniusweb_bridge/anac2020/bling_bling/bling_bling.py
negmas_geniusweb_bridge/anac2020/duo_agent/__init__.py
negmas_geniusweb_bridge/anac2020/duo_agent/duo_agent.py
negmas_geniusweb_bridge/anac2020/for_arisa/__init__.py
negmas_geniusweb_bridge/anac2020/for_arisa/for_arisa.py
negmas_geniusweb_bridge/anac2020/hamming_agent/__init__.py
negmas_geniusweb_bridge/anac2020/hamming_agent/hamming_agent.py
negmas_geniusweb_bridge/anac2020/nice_agent/__init__.py
negmas_geniusweb_bridge/anac2020/nice_agent/nice_agent.py
negmas_geniusweb_bridge/anac2020/shine_agent/__init__.py
negmas_geniusweb_bridge/anac2020/shine_agent/shine_agent.py
negmas_geniusweb_bridge/anac2020/utils.py
negmas_geniusweb_bridge/anac2021/__init__.py
negmas_geniusweb_bridge/anac2021/agent_fo2021/__init__.py
negmas_geniusweb_bridge/anac2021/agent_fo2021/agent_fo2021.py
negmas_geniusweb_bridge/anac2021/alpha_biu/__init__.py
negmas_geniusweb_bridge/anac2021/alpha_biu/alpha_biu.py
negmas_geniusweb_bridge/anac2021/dice_haggler/__init__.py
negmas_geniusweb_bridge/anac2021/dice_haggler/dice_haggler.py
negmas_geniusweb_bridge-0.1.2.dist-info/WHEEL
negmas_geniusweb_bridge-0.1.2.dist-info/METADATA
negmas_geniusweb_bridge-0.1.2.dist-info/RECORD
