Metadata-Version: 2.3
Name: negmas-geniusweb-bridge
Version: 0.1.2
Summary: A bridge that allows you to run GeniusWeb agents in negmas SAOMechanism(s).
Author: Yasser Mohammad
Author-email: Yasser Mohammad <yasserfarouk@gmail.com>
License: Academic and Non-Commercial Use License
Requires-Dist: negmas>=0.14.0
Requires-Dist: geniusweb
Requires-Dist: pyson
Requires-Dist: tudelft-utilities
Requires-Dist: tudelft-utilities-logging
Requires-Dist: uri
Requires-Dist: plotly>=6.5.0
Requires-Python: >=3.13
